LICENSE
LICENSE.txt
README.md
setup.py
movecolumn/__init__.py
movecolumn.egg-info/PKG-INFO
movecolumn.egg-info/SOURCES.txt
movecolumn.egg-info/dependency_links.txt
movecolumn.egg-info/top_level.txt