Metadata-Version: 2.1
Name: movecolumn
Version: 0.0.6
Summary: A creative package to move columns in Python dataframes.
Home-page: https://github.com/saadbinmunir/Calendric-lib.git
Author: Saad Bin Munir
Author-email: saadmunir24@gmail.com
License: Apache License 2.0
Platform: UNKNOWN
Classifier: Development Status :: 5 - Production/Stable
Classifier: Intended Audience :: Science/Research
Classifier: Intended Audience :: Developers
Classifier: Programming Language :: Python :: 3
Classifier: Topic :: Software Development
Classifier: Topic :: Scientific/Engineering
Classifier: Typing :: Typed
Classifier: Operating System :: MacOS :: MacOS X
Classifier: Operating System :: Microsoft :: Windows
License-File: LICENSE
License-File: LICENSE.txt
